botlogging/__init__.py
botlogging/delayed.py
botlogging/embed.py
botlogging/logger.py
botlogging-2.0.0.dist-info/METADATA
botlogging-2.0.0.dist-info/WHEEL
botlogging-2.0.0.dist-info/top_level.txt
botlogging-2.0.0.dist-info/RECORD
