Metadata-Version: 2.1
Name: botlogging
Version: 2.0.0
Summary: A logging package for Discord bots
Home-page: https://github.com/effprime/BotLogging
Author: effprime
Author-email: effprime@github.com
Project-URL: Bug Tracker, https://github.com/effprime/BotLogging/issues
Classifier: Programming Language :: Python :: 3
Classifier: License :: OSI Approved :: MIT License
Classifier: Operating System :: OS Independent
Requires-Python: >=3.6
